{
  "run_id": "174dd86a-6571-4350-8b2c-1862d9e8756c",
  "date": "2026-05-21",
  "mode": "IA",
  "dry_run": false,
  "portfolio": {
    "total_value": 10089146.93,
    "cash": 1225357.7981651379,
    "invested": 8775000.0,
    "total_pnl": 89146.93,
    "total_pnl_pct": 0.8914692999999999,
    "active_positions": 11
  },
  "actions": {
    "buy": [],
    "sell": [],
    "hold": [
      {
        "ticker": "ETERNAL.NS",
        "name": "Eternal Ltd.",
        "action": "HOLD",
        "r_asre": 73.9,
        "current_price": 243.34,
        "reason": "HOLD: score stable at 73.9; drop from prior=4.1pts; F=66/T=17/M=44; technicals intact",
        "priority": 99,
        "suggested_allocation": 0,
        "explanation": "",
        "rotation_sell_of": "",
        "rotation_buy_of": "",
        "capital_haircut_used": 0.0
      },
      {
        "ticker": "MUTHOOTFIN.NS",
        "name": "Muthoot Finance Ltd.",
        "action": "HOLD",
        "r_asre": 72.8,
        "current_price": 3309.3,
        "reason": "HOLD: score stable at 72.8; drop from prior=0.3pts; F=82/T=5/M=39; technicals intact",
        "priority": 99,
        "suggested_allocation": 0,
        "explanation": "",
        "rotation_sell_of": "",
        "rotation_buy_of": "",
        "capital_haircut_used": 0.0
      },
      {
        "ticker": "PTCIL.NS",
        "name": "PTC Industries Ltd.",
        "action": "HOLD",
        "r_asre": 83.0,
        "current_price": 15796.0,
        "reason": "HOLD: score stable at 83.0; drop from prior=-3.0pts; F=62/T=56/M=39; technicals intact",
        "priority": 99,
        "suggested_allocation": 0,
        "explanation": "",
        "rotation_sell_of": "",
        "rotation_buy_of": "",
        "capital_haircut_used": 0.0
      },
      {
        "ticker": "PAYTM.NS",
        "name": "Paytm",
        "action": "HOLD",
        "r_asre": 83.0,
        "current_price": 1153.5,
        "reason": "HOLD: score stable at 83.0; drop from prior=1.2pts; F=58/T=34/M=42; technicals intact",
        "priority": 99,
        "suggested_allocation": 0,
        "explanation": "",
        "rotation_sell_of": "",
        "rotation_buy_of": "",
        "capital_haircut_used": 0.0
      },
      {
        "ticker": "AMBER.NS",
        "name": "Amber Enterprises",
        "action": "HOLD",
        "r_asre": 77.3,
        "current_price": 7049.5,
        "reason": "HOLD: score stable at 77.3; drop from prior=-1.1pts; F=82/T=94/M=93; technicals intact",
        "priority": 99,
        "suggested_allocation": 0,
        "explanation": "",
        "rotation_sell_of": "",
        "rotation_buy_of": "",
        "capital_haircut_used": 0.0
      },
      {
        "ticker": "TVSMOTOR.NS",
        "name": "TVS Motor Company",
        "action": "HOLD",
        "r_asre": 80.0,
        "current_price": 3361.9,
        "reason": "HOLD: score stable at 80.0; drop from prior=0.6pts; F=67/T=87/M=32; technicals intact",
        "priority": 99,
        "suggested_allocation": 0,
        "explanation": "",
        "rotation_sell_of": "",
        "rotation_buy_of": "",
        "capital_haircut_used": 0.0
      },
      {
        "ticker": "MOTHERSON.NS",
        "name": "Motherson International",
        "action": "HOLD",
        "r_asre": 73.3,
        "current_price": 132.17,
        "reason": "HOLD: score stable at 73.3; drop from prior=4.3pts; F=67/T=93/M=46; technicals intact",
        "priority": 99,
        "suggested_allocation": 0,
        "explanation": "",
        "rotation_sell_of": "",
        "rotation_buy_of": "",
        "capital_haircut_used": 0.0
      },
      {
        "ticker": "BAJFINANCE.NS",
        "name": "Bajaj Finance",
        "action": "HOLD",
        "r_asre": 74.3,
        "current_price": 923.1,
        "reason": "HOLD: score stable at 74.3; drop from prior=1.5pts; F=67/T=95/M=47; technicals intact",
        "priority": 99,
        "suggested_allocation": 0,
        "explanation": "",
        "rotation_sell_of": "",
        "rotation_buy_of": "",
        "capital_haircut_used": 0.0
      },
      {
        "ticker": "PRESTIGE.NS",
        "name": "Prestige Estates",
        "action": "HOLD",
        "r_asre": 74.7,
        "current_price": 1387.8,
        "reason": "HOLD: score stable at 74.7; drop from prior=3.5pts; F=78/T=93/M=34; technicals intact",
        "priority": 99,
        "suggested_allocation": 0,
        "explanation": "",
        "rotation_sell_of": "",
        "rotation_buy_of": "",
        "capital_haircut_used": 0.0
      },
      {
        "ticker": "V2RETAIL.NS",
        "name": "V2 Retail",
        "action": "HOLD",
        "r_asre": 72.9,
        "current_price": 227.28,
        "reason": "HOLD: score stable at 72.9; drop from prior=-1.1pts; F=82/T=20/M=100; technicals intact",
        "priority": 99,
        "suggested_allocation": 0,
        "explanation": "",
        "rotation_sell_of": "",
        "rotation_buy_of": "",
        "capital_haircut_used": 0.0
      },
      {
        "ticker": "SBIN.NS",
        "name": "State Bank of India",
        "action": "HOLD",
        "r_asre": 78.2,
        "current_price": 950.9,
        "reason": "HOLD: score stable at 78.2; drop from prior=1.0pts; F=66/T=78/M=23; technicals intact",
        "priority": 99,
        "suggested_allocation": 0,
        "explanation": "",
        "rotation_sell_of": "",
        "rotation_buy_of": "",
        "capital_haircut_used": 0.0
      }
    ],
    "watch": []
  },
  "rotation_swaps": [],
  "transactions": [],
  "score_hash": "ebbcba7af84c9cfbd3a9c7c2ffc7e811"
}